truffleHogRegexes/__init__.py
truffleHogRegexes/regexChecks.py
truffleHogRegexes/regexes.json
truffleHogRegexes-0.0.6.dist-info/METADATA
truffleHogRegexes-0.0.6.dist-info/RECORD
truffleHogRegexes-0.0.6.dist-info/WHEEL
truffleHogRegexes-0.0.6.dist-info/top_level.txt
