Metadata-Version: 2.1
Name: truffleHogRegexes
Version: 0.0.6
Summary: These regexes power truffleHog.
Home-page: https://github.com/dxa4481/truffleHogRegexes
Author: Dylan Ayrey
Author-email: dylanayrey@gmail.com
License: GNU
Platform: UNKNOWN
